aptbox/__init__.py
aptbox/main.py
aptbox/analyze/__init__.py
aptbox/analyze/dependency.py
aptbox/analyze/manager.py
aptbox/analyze/risk.py
aptbox/analyze/security.py
aptbox/apt/__init__.py
aptbox/apt/manager.py
aptbox/compare/__init__.py
aptbox/compare/comparer.py
aptbox/report/__init__.py
aptbox/report/generator.py
aptbox/report/manager.py
aptbox/snapshot/__init__.py
aptbox/snapshot/manager.py
aptbox-0.1.1.data/data/etc/bash_completion.d/aptbox-completion.bash
aptbox-0.1.1.dist-info/licenses/LICENSE
aptbox-0.1.1.dist-info/METADATA
aptbox-0.1.1.dist-info/WHEEL
aptbox-0.1.1.dist-info/entry_points.txt
aptbox-0.1.1.dist-info/top_level.txt
aptbox-0.1.1.dist-info/RECORD
