Metadata-Version: 2.4
Name: aptbox
Version: 0.1.1
Summary: APT软件包快照与比较工具
Home-page: https://github.com/fengyucn/aptbox
Author: fengyucn
Author-email: fengyucn <fengyucn@gmail.com>
Maintainer-email: fengyucn <fengyucn@gmail.com>
License: MIT License
Project-URL: Homepage, https://github.com/fengyucn/aptbox
Project-URL: Repository, https://github.com/fengyucn/aptbox
Project-URL: Documentation, https://github.com/fengyucn/aptbox/blob/main/README.md
Project-URL: Bug Reports, https://github.com/fengyucn/aptbox/issues
Keywords: apt,debian,ubuntu,package management,snapshot,system administration
Classifier: Development Status :: 4 - Beta
Classifier: Intended Audience :: System Administrators
Classifier: Intended Audience :: Developers
Classifier: Topic :: System :: Systems Administration
Classifier: Topic :: Software Development :: Libraries :: Python Modules
Classifier: License :: OSI Approved :: MIT License
Classifier: Programming Language :: Python :: 3
Classifier: Programming Language :: Python :: 3.6
Classifier: Programming Language :: Python :: 3.7
Classifier: Programming Language :: Python :: 3.8
Classifier: Programming Language :: Python :: 3.9
Classifier: Programming Language :: Python :: 3.10
Classifier: Programming Language :: Python :: 3.11
Classifier: Programming Language :: Python :: 3.12
Classifier: Operating System :: POSIX :: Linux
Classifier: Environment :: Console
Requires-Python: >=3.6
License-File: LICENSE
Requires-Dist: packaging
Provides-Extra: dev
Requires-Dist: pytest>=6.0; extra == "dev"
Requires-Dist: pytest-cov; extra == "dev"
Requires-Dist: black; extra == "dev"
Requires-Dist: flake8; extra == "dev"
Requires-Dist: mypy; extra == "dev"
Dynamic: author
Dynamic: home-page
Dynamic: license-file
Dynamic: requires-python
